<?xml version="1.0" encoding="UTF-8"?>
<databaseChangeLog
        xmlns="http://www.liquibase.org/xml/ns/dbchangelog"
        xmlns:xsi="http://www.w3.org/2001/XMLSchema-instance"
        xsi:schemaLocation="http://www.liquibase.org/xml/ns/dbchangelog
   http://www.liquibase.org/xml/ns/dbchangelog/dbchangelog-3.4.xsd">

    <changeSet id="20082017-1-1" author="caramel">
        <addColumn tableName="guild_config">
            <column name="is_help_private" type="BOOLEAN"/>
        </addColumn>
    </changeSet>

    <changeSet id="20082017-1-2" author="caramel">
        <createTable tableName="web_hook">
            <column name="id" type="BIGSERIAL">
                <constraints nullable="false" primaryKey="true" primaryKeyName="pk_web_hook"/>
            </column>
            <column name="version" type="BIGINT"/>
            <column name="hook_id" type="BIGINT" />
            <column name="token" type="VARCHAR(255)" />
            <column name="enabled" type="BOOLEAN" />
        </createTable>
    </changeSet>

    <changeSet id="20082017-1-3" author="caramel">
        <addColumn tableName="guild_config">
            <column name="web_hook_id" type="BIGINT">
                <constraints nullable="true" foreignKeyName="fk_guild_config_web_hook" references="web_hook(id)" />
            </column>
        </addColumn>
    </changeSet>

    <changeSet id="20082017-1-4" author="caramel">
        <delete tableName="auto_post" />
    </changeSet>

</databaseChangeLog>